[{"timestamp_utc":"2023-05-13T12:39:22.765Z","context_application_version":"8.8.32.508","context_conn_country":"BR","context_device_manufacturer":"samsung","context_device_model":"SM-N986B","context_os_name":"android","context_os_version":"13","context_receiver_service_timestamp":1683981623199,"context_time":1683981562765,"message_error_description":"Updating token failed with error HTTP 503 Could not retrieve access token for a webgate request: https://spclient.wg.spotify.com/pushka-tokens/register/v3 with error: sp://auth/v2/token responded with an error: 5, oauth:5","message_timestamp_ms":1683981562764}]